LICENSE
MANIFEST.in
README.md
pyproject.toml
setup.py
hypertree/__init__.py
hypertree/_version.py
hypertree/base.py
hypertree/melter.py
hypertree.egg-info/PKG-INFO
hypertree.egg-info/SOURCES.txt
hypertree.egg-info/dependency_links.txt
hypertree.egg-info/not-zip-safe
hypertree.egg-info/requires.txt
hypertree.egg-info/top_level.txt
hypertree/ensemble/__init__.py
hypertree/ensemble/_forest.py
hypertree/matrix_factorization/__init__.py
hypertree/matrix_factorization/_nrlmf.py
hypertree/model_selection/__init__.py
hypertree/model_selection/_search.py
hypertree/model_selection/_split.py
hypertree/model_selection/_validation.py
hypertree/tree/__init__.py
hypertree/tree/_nd_classes.py
hypertree/tree/_nd_criterion.c
hypertree/tree/_nd_criterion.pxd
hypertree/tree/_nd_splitter.c
hypertree/tree/_nd_splitter.pxd
hypertree/tree/_nd_tree.cpp
hypertree/tree/_nd_tree.pxd
hypertree/tree/_semisupervised_criterion.c
hypertree/tree/setup.py
hypertree/utils/__init__.py