Metadata-Version: 2.1
Name: hypertree
Version: 0.3.2.dev0
Summary: HyperTrees in Python.
Home-page: http://github.com/pedroilidio/hypertree
Author: Pedro Ilídio
Author-email: pedrilidio@gmail.com
License: new BSD
Platform: UNKNOWN
License-File: LICENSE
